katvi/__init__.py
katvi/button.py
katvi/core.py
katvi/window.py
katvi-0.1.0.dist-info/METADATA
katvi-0.1.0.dist-info/WHEEL
katvi-0.1.0.dist-info/top_level.txt
katvi-0.1.0.dist-info/RECORD
